{"displayProperties":{"description":"","name":"","hasIcon":false},"unlockValueHash":0,"completionValue":1,"scope":5,"locationHash":1778248786,"allowNegativeValue":false,"allowValueChangeWhenCompleted":false,"isCountingDownward":false,"valueStyle":0,"progressDescription":"The Tower is abuzz with the news that you and Petra avenged the death of Cayde-6. Tess Everis has a gift for you from Eververse.","perks":{"perkHash":0,"style":0},"stats":{"style":0},"minimumVisibilityThreshold":-2147483648,"allowOvercompletion":false,"showValueOnComplete":false,"isDisplayOnlyObjective":false,"completedValueStyle":0,"inProgressValueStyle":0,"hash":1472418532,"index":2334,"redacted":false,"blacklisted":false}