{"displayProperties":{"description":"Tracks the number of Izanami Forge ignitions completed.","name":"Blood of Izanami","icon":"/common/destiny2_content/icons/4a08ae6b1321d3d16787fed1aeb6b096.jpg","hasIcon":true},"scope":0,"sourceString":"Source: Complete the \"Reunited Siblings\" Triumph.","sourceHash":1457456824,"itemHash":3491436641,"acquisitionInfo":{"runOnlyAcquisitionRewardSite":false},"stateInfo":{"requirements":{"entitlementUnavailableMessage":"Requires Annual Pass"}},"presentationInfo":{"presentationNodeType":1,"parentPresentationNodeHashes":[2454690454],"displayStyle":3},"hash":2063294363,"index":1949,"redacted":false,"blacklisted":false}