{"displayProperties":{"description":"\"Nowhere but up!\" \u2014Marcus Ren","name":"Upward Spiral","icon":"/common/destiny2_content/icons/d7af459336c5edcabe47e5ed32298df2.jpg","hasIcon":true},"scope":0,"sourceString":"Source: Eververse package.","sourceHash":269962496,"itemHash":3600237171,"acquisitionInfo":{"acquireMaterialRequirementHash":1514656542,"runOnlyAcquisitionRewardSite":false},"stateInfo":{"requirements":{"entitlementUnavailableMessage":""}},"presentationInfo":{"presentationNodeType":1,"parentPresentationNodeHashes":[2864084213],"displayStyle":3},"hash":2246328454,"index":2579,"redacted":false,"blacklisted":false}