{"displayProperties":{"description":"\"Do we need another reminder? This world is but a grave.\" \u2014Arach Jalaal","name":"Hollow Earth","icon":"/common/destiny2_content/icons/a7bc7f7c1b99c4b10f8aed3154bb5a9d.jpg","hasIcon":true},"scope":1,"sourceString":"Source: Earn rank-up packages from Arach Jalaal.","sourceHash":146504277,"itemHash":1842303080,"acquisitionInfo":{"acquireMaterialRequirementHash":983547049,"runOnlyAcquisitionRewardSite":false},"stateInfo":{"requirements":{"entitlementUnavailableMessage":"Requires Destiny 2: Curse of Osiris"}},"presentationInfo":{"presentationNodeType":2,"parentPresentationNodeHashes":[2766676737],"displayStyle":3},"hash":256984757,"index":3123,"redacted":false,"blacklisted":false}