{"displayProperties":{"description":"Quiet but deadly.","name":"Subtle Calamity","icon":"/common/destiny2_content/icons/fcd692e310cae52471d599faa53a5508.jpg","hasIcon":true},"scope":0,"sourceString":"Source: Open Legendary engrams and earn faction rank-up packages.","sourceHash":3334812276,"itemHash":3410721600,"acquisitionInfo":{"runOnlyAcquisitionRewardSite":false},"stateInfo":{"requirements":{"entitlementUnavailableMessage":"Requires Destiny 2: Forsaken"}},"presentationInfo":{"presentationNodeType":2,"parentPresentationNodeHashes":[2976016363],"displayStyle":3},"hash":301231526,"index":3150,"redacted":false,"blacklisted":false}