{"displayProperties":{"description":"This emblem tracks your high score for the Nightfall \"The Pyramidion.\"","name":"The Pyramidion","icon":"/common/destiny2_content/icons/2b6160e0f21e748cd996b404771a850c.jpg","hasIcon":true},"scope":1,"sourceString":"Source: Complete Nightfall strike \"The Pyramidion.\"","sourceHash":2717017239,"itemHash":10493725,"acquisitionInfo":{"runOnlyAcquisitionRewardSite":false},"stateInfo":{"requirements":{"entitlementUnavailableMessage":""}},"presentationInfo":{"presentationNodeType":1,"parentPresentationNodeHashes":[2454690454],"displayStyle":3},"hash":3490589930,"index":1916,"redacted":false,"blacklisted":false}