{"displayProperties":{"description":"Defeat enemies with Sniper Rifles in the Crucible during Season 3 to unlock and equip this ornament.","name":"Fire-Forged Hunter Leg Ornament","icon":"/common/destiny2_content/icons/cac7374b73e94d0c469c7c7a4dcc1d3e.jpg","hasIcon":true},"scope":1,"sourceString":"","sourceHash":3389857033,"itemHash":3906326418,"acquisitionInfo":{"runOnlyAcquisitionRewardSite":false},"stateInfo":{"requirements":{"entitlementUnavailableMessage":""}},"presentationInfo":{"presentationNodeType":2,"parentPresentationNodeHashes":[1633867908],"displayStyle":3},"hash":3840674369,"index":13,"redacted":false,"blacklisted":false}