{"displayProperties":{"description":"\"Do I miss my arm? I miss my empire. I would give everything to have it back. And I will.\" \u2014Valus Nohr","name":"Gauntlets of Nohr","icon":"/common/destiny2_content/icons/0e9852739877eb747ad6b1ef6efb3063.jpg","hasIcon":true},"scope":1,"sourceString":"Source: Leviathan, Eater of Worlds raid lair.","sourceHash":2937902448,"itemHash":666883012,"acquisitionInfo":{"acquireMaterialRequirementHash":983547049,"runOnlyAcquisitionRewardSite":false},"stateInfo":{"requirements":{"entitlementUnavailableMessage":"Requires Destiny 2: Curse of Osiris"}},"presentationInfo":{"presentationNodeType":2,"parentPresentationNodeHashes":[1847361713],"displayStyle":3},"hash":3910680404,"index":667,"redacted":false,"blacklisted":false}