{"displayProperties":{"description":"\"What kind of harebrained scheme have you got in mind this time?\"","name":"The Jade Rabbit","icon":"/common/destiny2_content/icons/65a42d35f066e7c06861a1a416388f4b.jpg","hasIcon":true},"scope":0,"sourceString":"Source: Exotic engrams; extremely rare world drops.","sourceHash":1563875874,"itemHash":3844694310,"acquisitionInfo":{"acquireMaterialRequirementHash":1920773870,"runOnlyAcquisitionRewardSite":false},"stateInfo":{"requirements":{"entitlementUnavailableMessage":"Requires Destiny 2: Curse of Osiris"}},"presentationInfo":{"presentationNodeType":2,"parentPresentationNodeHashes":[454888209,2283697615,1367826044,2969886327],"displayStyle":3},"hash":564802915,"index":1629,"redacted":false,"blacklisted":false}