{"displayProperties":{"description":"Tracks Guided Game raid encounters in the \"Last Wish\" raid.","name":"Apprentice Guide","icon":"/common/destiny2_content/icons/1df4850522d70a4a29f15175c9a989cd.jpg","hasIcon":true},"scope":0,"sourceString":"","sourceHash":3389857033,"itemHash":1053023441,"acquisitionInfo":{"runOnlyAcquisitionRewardSite":false},"stateInfo":{"requirements":{"entitlementUnavailableMessage":""}},"presentationInfo":{"presentationNodeType":1,"parentPresentationNodeHashes":[2454690454],"displayStyle":3},"hash":845401762,"index":1896,"redacted":false,"blacklisted":false}