{"displayProperties":{"description":"Once your team holds enough Motes to summon a Primeval, deposit your Motes without picking up more.","name":"Following Instructions","icon":"/common/destiny2_content/icons/5369002dc68e7f2afd56f9b9be38a542.png","hasIcon":true},"scope":0,"presentationInfo":{"presentationNodeType":3,"parentPresentationNodeHashes":[2113699645],"displayStyle":4},"objectiveHashes":[2209174171],"recordValueStyle":0,"titleInfo":{"hasTitle":false},"completionInfo":{"partialCompletionObjectiveCountThreshold":0,"ScoreValue":100,"shouldFireToast":true,"toastStyle":1},"stateInfo":{"featuredPriority":2147483647,"completeUnlockHash":0,"claimedUnlockHash":0},"requirements":{"entitlementUnavailableMessage":""},"expirationInfo":{"hasExpiration":false,"description":""},"rewardItems":[],"hash":2053529794,"index":1425,"redacted":false,"blacklisted":false}