{"displayProperties":{"description":"Reach Power level 500.","name":"Evolution of a Titan","icon":"/common/destiny2_content/icons/e78f012b19b5f6c6026c12547895b756.png","hasIcon":true},"scope":0,"presentationInfo":{"presentationNodeType":3,"parentPresentationNodeHashes":[2761465119],"displayStyle":4},"objectiveHashes":[4066369059],"recordValueStyle":0,"titleInfo":{"hasTitle":false},"completionInfo":{"partialCompletionObjectiveCountThreshold":0,"ScoreValue":150,"shouldFireToast":true,"toastStyle":1},"stateInfo":{"featuredPriority":2147483647,"completeUnlockHash":0,"claimedUnlockHash":0},"requirements":{"entitlementUnavailableMessage":""},"expirationInfo":{"hasExpiration":false,"description":""},"rewardItems":[],"hash":3002736314,"index":309,"redacted":false,"blacklisted":false}