{"displayProperties":{"description":"Defeat targets with precision final blows on Io. Earn bonus progress in Heroic adventures and Lost Sectors.","name":"Terraformed Calibration","icon":"/common/destiny2_content/icons/0504929d93d9063d6529e36067a82191.png","hasIcon":true},"backgroundColor":{"colorHash":0,"red":0,"green":0,"blue":0,"alpha":0},"itemTypeDisplayName":"Weekly Bounty","uiItemDisplayStyle":"","itemTypeAndTierDisplayName":"Rare Weekly Bounty","displaySource":"\"Used to go cliffdiving with Cayde on the Mesa, 'til I got too creaky.\" \u2014Banshee-44","tooltipStyle":"build","action":{"verbName":"Abandon","verbDescription":"","isPositive":false,"requiredCooldownSeconds":0,"requiredItems":[],"progressionRewards":[],"rewardSheetHash":0,"rewardItemHash":0,"rewardSiteHash":0,"requiredCooldownHash":0,"deleteOnAction":true,"consumeEntireStack":false,"useOnAcquire":false},"inventory":{"stackUniqueLabel":"v450.bounties.gunsmith.weekly.destination_io","maxStackSize":1,"bucketTypeHash":1345459588,"recoveryBucketTypeHash":0,"tierTypeHash":2127292149,"isInstanceItem":true,"nonTransferrableOriginal":false,"tierTypeName":"Rare","tierType":4,"expirationTooltip":"Expires in .","expiredInActivityMessage":"Expired. Unless completed, this bounty will be removed when you return to orbit or load into a new activity.","expiredInOrbitMessage":"Expired. Bounty will be removed upon leaving orbit.","suppressExpirationWhenObjectivesComplete":true},"stats":{"disablePrimaryStatDisplay":false,"stats":{},"hasDisplayableStats":false,"primaryBaseStatHash":0},"value":{"itemValue":[{"itemHash":2654582465,"quantity":0},{"itemHash":3853748946,"quantity":0},{"itemHash":1305274547,"quantity":10},{"itemHash":0,"quantity":0},{"itemHash":0,"quantity":0},{"itemHash":0,"quantity":0}],"valueDescription":""},"sourceData":{"sourceHashes":[],"sources":[{"level":0,"minQuality":0,"maxQuality":0,"minLevelRequired":0,"maxLevelRequired":0,"exclusivity":0,"computedStats":{},"sourceHashes":[]}],"exclusive":0,"vendorSources":[{"vendorHash":672118013,"vendorItemIndexes":[77]}]},"objectives":{"objectiveHashes":[3238727990],"displayActivityHashes":[2166136261],"requireFullObjectiveCompletion":true,"questlineItemHash":0,"narrative":"","objectiveVerbName":"Claim Bounty","questTypeIdentifier":"patrol_tier1","questTypeHash":18743735,"completionRewardSiteHash":0,"nextQuestStepRewardSiteHash":0,"timestampUnlockValueHash":0,"isGlobalObjectiveItem":false,"useOnObjectiveCompletion":false,"inhibitCompletionUnlockValueHash":0,"perObjectiveDisplayProperties":[{"displayOnItemPreviewScreen":false}]},"acquireRewardSiteHash":0,"acquireUnlockHash":0,"investmentStats":[],"perks":[],"allowActions":true,"doesPostmasterPullHaveSideEffects":false,"nonTransferrable":true,"itemCategoryHashes":[579365201,1784235469],"specialItemType":0,"itemType":26,"itemSubType":0,"classType":3,"equippable":false,"defaultDamageType":0,"isWrapper":false,"hash":1029832908,"index":10121,"redacted":false,"blacklisted":false}